unistat/__init__.py
unistat/_types.py
unistat/contingency.py
unistat/continuous.py
unistat/exceptions.py
unistat/regression.py
unistat/resampling.py
unistat-0.2.3.dist-info/METADATA
unistat-0.2.3.dist-info/WHEEL
unistat-0.2.3.dist-info/entry_points.txt
unistat-0.2.3.dist-info/RECORD
