Metadata-Version: 2.4
Name: unistat
Version: 0.2.3
Summary: A unified statistics interface for running and displaying simple stats, using SciPy and statsmodels.
Author-email: "David Limon, MD" <dclimon@gmail.com>
Requires-Python: >=3.11
Requires-Dist: numpy>=2.0.0
Requires-Dist: pandas>=2.0.0
Requires-Dist: scipy>=1.10.0
Requires-Dist: statsmodels>=0.14.0
